odoo/addons/stock_inventory_valuation_report/README.rst
odoo/addons/stock_inventory_valuation_report/__init__.py
odoo/addons/stock_inventory_valuation_report/__manifest__.py
odoo/addons/stock_inventory_valuation_report/data/paperformat_data.xml
odoo/addons/stock_inventory_valuation_report/i18n/fr.po
odoo/addons/stock_inventory_valuation_report/i18n/it.po
odoo/addons/stock_inventory_valuation_report/i18n/pt.po
odoo/addons/stock_inventory_valuation_report/i18n/sl.po
odoo/addons/stock_inventory_valuation_report/i18n/stock_inventory_valuation_report.pot
odoo/addons/stock_inventory_valuation_report/readme/CONTRIBUTORS.rst
odoo/addons/stock_inventory_valuation_report/readme/DESCRIPTION.rst
odoo/addons/stock_inventory_valuation_report/readme/USAGE.rst
odoo/addons/stock_inventory_valuation_report/reports/__init__.py
odoo/addons/stock_inventory_valuation_report/reports/stock_inventory_valuation_report.py
odoo/addons/stock_inventory_valuation_report/reports/stock_inventory_valuation_report.xml
odoo/addons/stock_inventory_valuation_report/reports/stock_inventory_valuation_report_xlsx.py
odoo/addons/stock_inventory_valuation_report/security/ir.model.access.csv
odoo/addons/stock_inventory_valuation_report/static/description/icon.png
odoo/addons/stock_inventory_valuation_report/static/description/index.html
odoo/addons/stock_inventory_valuation_report/static/src/css/report.css
odoo/addons/stock_inventory_valuation_report/static/src/js/stock_inventory_valuation_report_backend.js
odoo/addons/stock_inventory_valuation_report/tests/__init__.py
odoo/addons/stock_inventory_valuation_report/tests/test_stock_inventory_valuation_report.py
odoo/addons/stock_inventory_valuation_report/wizard/__init__.py
odoo/addons/stock_inventory_valuation_report/wizard/stock_quantity_history.py
odoo/addons/stock_inventory_valuation_report/wizard/stock_quantity_history_view.xml
odoo14_addon_stock_inventory_valuation_report-14.0.1.0.1.dev6.dist-info/METADATA
odoo14_addon_stock_inventory_valuation_report-14.0.1.0.1.dev6.dist-info/WHEEL
odoo14_addon_stock_inventory_valuation_report-14.0.1.0.1.dev6.dist-info/top_level.txt
odoo14_addon_stock_inventory_valuation_report-14.0.1.0.1.dev6.dist-info/RECORD
